MANIFEST.in
README.md
setup.py
bootd/__init__.py
bootd.egg-info/PKG-INFO
bootd.egg-info/SOURCES.txt
bootd.egg-info/dependency_links.txt
bootd.egg-info/requires.txt
bootd.egg-info/top_level.txt
bootd/bin/bootd-admin.py
bootd/bin/bootd-admin.py
bootd/project_template/fabfile.py
bootd/project_template/manage.py
bootd/project_template/secrets.json.example
bootd/project_template/project_name/__init__.py
bootd/project_template/project_name/common_settings.py
bootd/project_template/project_name/settings.py
bootd/project_template/project_name/urls.py
bootd/project_template/project_name/wsgi.py
bootd/project_template/templates/base.html