Metadata-Version: 1.1
Name: bootd
Version: 1.0.8
Summary: Wizard startproject from django base template.
Home-page: http://github.com/shinznatkid/bootd
Author: ShinZ Natkid
Author-email: shinznatkid@gmail.com
License: MIT
Platform: UNKNOWN
Classifier: Development Status :: 3 - Alpha
Classifier: Programming Language :: Python :: 2.7
